tspex/__init__.py
tspex/cli.py
tspex/core/__init__.py
tspex/core/auxiliary_functions.py
tspex/core/specificity_class.py
tspex/core/specificity_functions.py
tspex-0.6.2.dist-info/LICENSE
tspex-0.6.2.dist-info/METADATA
tspex-0.6.2.dist-info/WHEEL
tspex-0.6.2.dist-info/entry_points.txt
tspex-0.6.2.dist-info/top_level.txt
tspex-0.6.2.dist-info/RECORD
